setup.py
legos/__init__.py
legos/wtf.py
legos.wtf.egg-info/PKG-INFO
legos.wtf.egg-info/SOURCES.txt
legos.wtf.egg-info/dependency_links.txt
legos.wtf.egg-info/namespace_packages.txt
legos.wtf.egg-info/requires.txt
legos.wtf.egg-info/top_level.txt