Metadata-Version: 1.1
Name: legos.wtf
Version: 0.1.2
Summary: Wikipedia Top Finder plugin for Legobot
Home-page: https://github.com/bbriggs/legos.wtf
Author: Brenton Briggs II
Author-email: UNKNOWN
License: GPLv3
Platform: UNKNOWN
Classifier: License :: OSI Approved :: GNU General Public License v3 (GPLv3)
Classifier: Programming Language :: Python :: 3
